{
  "url": "http://127.0.0.1:8000/",
  "connections": 2,
  "sampleInt": 1000,
  "pipelining": 1,
  "workers": 0,
  "duration": 1.07,
  "samples": 1,
  "start": "2023-08-21T16:21:42.796Z",
  "finish": "2023-08-21T16:21:43.863Z",
  "errors": 0,
  "timeouts": 0,
  "mismatches": 0,
  "non2xx": 2,
  "resets": 0,
  "1xx": 0,
  "2xx": 0,
  "3xx": 0,
  "4xx": 2,
  "5xx": 0,
  "statusCodeStats": {
    "400": {
      "count": 2
    }
  },
  "latency": {
    "average": 913.5,
    "mean": 913.5,
    "stddev": 0.5,
    "min": 913,
    "max": 914,
    "p0_001": 913,
    "p0_01": 913,
    "p0_1": 913,
    "p1": 913,
    "p2_5": 913,
    "p10": 913,
    "p25": 913,
    "p50": 913,
    "p75": 914,
    "p90": 914,
    "p97_5": 914,
    "p99": 914,
    "p99_9": 914,
    "p99_99": 914,
    "p99_999": 914,
    "totalCount": 2
  },
  "requests": {
    "average": 2,
    "mean": 2,
    "stddev": 0,
    "min": 2,
    "max": 2,
    "total": 2,
    "p0_001": 2,
    "p0_01": 2,
    "p0_1": 2,
    "p1": 2,
    "p2_5": 2,
    "p10": 2,
    "p25": 2,
    "p50": 2,
    "p75": 2,
    "p90": 2,
    "p97_5": 2,
    "p99": 2,
    "p99_9": 2,
    "p99_99": 2,
    "p99_999": 2,
    "sent": 2
  },
  "throughput": {
    "average": 2125,
    "mean": 2125,
    "stddev": 0,
    "min": 2124,
    "max": 2124,
    "total": 2124,
    "p0_001": 2125,
    "p0_01": 2125,
    "p0_1": 2125,
    "p1": 2125,
    "p2_5": 2125,
    "p10": 2125,
    "p25": 2125,
    "p50": 2125,
    "p75": 2125,
    "p90": 2125,
    "p97_5": 2125,
    "p99": 2125,
    "p99_9": 2125,
    "p99_99": 2125,
    "p99_999": 2125
  }
}